<?xml version="1.0" encoding="UTF-8" standalone="yes"?>
<informationSet xmlns="ec/tss.core">
    <item name="sa1">
        <subset>
            <item name="name">
                <string>VATPSA</string>
            </item>
            <item name="ts">
                <ts name="VATPSA">
                    <freq>12</freq>
                    <firstYear>2000</firstYear>
                    <firstPeriod>1</firstPeriod>
                    <data>3942834.0 4724152.0 5989172.0 7986603.0 9551654.0 1.2079901E7 1.2681958E7 1.1211946E7 1.2729476E7 8748318.0 4073128.0 3501978.0 4247068.0 5532331.0 6217127.0 8648710.0 1.0301489E7 1.2495388E7 1.3502961E7 1.1714363E7 1.2426866E7 8249238.0 3787576.0 3199237.0 3738115.0 4980469.0 6896391.0 7430257.0 1.1156913E7 1.1215459E7 1.2987334E7 1.1239247E7 1.2374272E7 8955982.0 3596726.0 3266002.0 3921451.0 4913065.0 6102033.0 7885844.0 9469590.0 1.1564527E7 1.2411547E7 1.0969535E7 1.137914E7 8465580.0 3443118.0 3409206.0 4095066.0 5570986.0 6331808.0 8298095.0 1.0359808E7 1.1246233E7 1.2470905E7 1.1044434E7 1.2160372E7 8603289.0 3777314.0 3216534.0 4484180.0 5566916.0 7791321.0 7360390.0 1.1187453E7 1.0966162E7 1.3273976E7 1.1667845E7 1.275304E7 9193840.0 4194909.0 3871879.0 4805614.0 6025076.0 6904313.0 8962359.0 1.094119E7 1.2412649E7 1.4113221E7 1.2360995E7 1.3630004E7 9654295.0 4306678.0 3742341.0 4777420.0 6026352.0 7420726.0 9212312.0 1.134637E7 1.2779481E7 1.501123E7 1.3345344E7 1.4206571E7 1.0157343E7 4604672.0 4129618.0 5088511.0 6305486.0 8386905.0 8053913.0 1.1591641E7 1.1667008E7 1.5196725E7 1.3062487E7 1.3388438E7 9422035.0 4209918.0 4118642.0 4923294.0 5894959.0 6672759.0 8676952.0 1.0245942E7 1.1561448E7 1.4870666E7 1.3310779E7 1.3263441E7 9376992.0 4023928.0 4007419.0 4721858.0 5879370.0 7251701.0 8394465.0 1.1092484E7 1.2055792E7 1.5767304E7 1.4050174E7 1.4049661E7 9855089.0 4360645.0 4072983.0 5058079.0 5789647.0 7498732.0 9637333.0 1.1056107E7 1.406457E7 1.7204213E7 1.5394552E7 1.5252911E7 1.0518678E7 4424390.0 4114815.0 5304079.0 6222376.0 7404284.0 9581301.0 1.1699551E7 1.3230623E7 1.737226E7 1.565454E7 1.5042567E7 1.0820798E7 4511281.0 4258335.0 5390836.0 6335825.0 8265338.0 8548177.0 1.296081E7 1.3810248E7 1.8426642E7 1.6829891E7 1.6083415E7 1.0684527E7 4445006.0 4549573.0 5518967.0 6334233.0 7792136.0 9873269.0 1.2039616E7 1.4695007E7 1.799606E7 1.7276081E7 1.6205953E7 1.0699519E7 4403474.0 4539425.0 5451953.0 6578844.0 7437440.0 9437753.0 1.2814651E7 1.4757799E7 1.8834428E7 1.7722687E7 1.6771856E7 1.1113257E7 4557716.0 4213407.0 5373339.0 6853375.0 8675202.0 8653413.0 1.3398392E7 1.4331401E7 1.9743689E7 1.7869015E7 1.6843399E7 1.1174815E7 4587072.0 4485595.0 5596951.0 6801978.0 7711682.0 1.0673267E7 1.2495987E7 1.6230304E7 2.1092394E7 1.8146613E7 1.7159404E7 1.1700525E7 4837684.0 4651904.0 5993219.0 7334181.0 9007168.0 1.0082037E7 1.4138306E7 1.5880848E7 2.0214013E7 1.7887466E7 1.7205658E7 1.1679825E7 4878387.0 4975325.0 6062127.0 7159923.0 8353828.0 1.0671833E7 1.3084276E7 1.7358931E7 1.9972827E7 1.7848338E7 1.7392193E7 1.2290831E7 5040059.0 5325965.0 6392972.0 6939218.0 856031.0 140145.0 198607.0 1078085.0 5013931.0 7020138.0 6968960.0 2967666.0 442585.0 324439.0 313768.0 423526.0 415507.0 419539.0 1634734.0 4962939.0 1.1007664E7 1.245755E7 1.1038047E7 7687598.0 3014328.0 3164256.0 3322891.0 4188123.0 5099997.0 7827004.0 1.0029469E7 1.3858338E7 1.6588456E7 1.6355264E7 1.508412E7 1.0418272E7 4202675.0 4583875.0 5444097.0 7356733.0 7073319.0 9646290.0</data>
                </ts>
            </item>
            <item name="domainspec">
                <string>spec1</string>
            </item>
        </subset>
    </item>
    <item name="domainspecs">
        <subset>
            <item name="spec1">
                <subset>
                    <item name="algorithm">
                        <method version="0.1.0.0">
                            <name>tramoseats</name>
                            <family>Seasonal adjustment</family>
                        </method>
                    </item>
                    <item name="tramo">
                        <subset>
                            <item name="algorithm">
<method version="0.1.0.0">
    <name>tramo</name>
    <family>Modelling</family>
</method>
                            </item>
                            <item name="transform">
<subset>
    <item name="function">
        <string>Log</string>
    </item>
</subset>
                            </item>
                            <item name="arima">
<subset>
    <item name="theta">
        <params>
            <coef/>
        </params>
    </item>
    <item name="btheta">
        <params>
            <coef/>
        </params>
    </item>
</subset>
                            </item>
                            <item name="automdl">
<subset>
    <item name="enabled">
        <boolean>false</boolean>
    </item>
</subset>
                            </item>
                            <item name="regression">
<subset>
    <item name="calendar">
        <subset>
            <item name="td">
                <subset>
                    <item name="user">
                        <strings>
                            <items>r._ts_external_1@PENT_DUR6_IEM_0</items>
                        </strings>
                    </item>
                </subset>
            </item>
            <item name="easter">
                <subset>
                    <item name="type">
                        <string>IncludeEaster</string>
                    </item>
                </subset>
            </item>
        </subset>
    </item>
    <item name="outliers">
        <strings>
            <items>AO.2020-03-01 AO.2020-04-01 AO.2020-05-01 AO.2020-06-01 AO.2020-07-01 AO.2020-08-01 AO.2020-09-01 AO.2020-10-01 AO.2020-11-01 AO.2020-12-01 AO.2021-01-01 AO.2021-02-01 AO.2021-03-01 AO.2021-04-01 TC.2021-05-01 AO.2021-09-01 AO.2021-10-01 AO.2021-11-01 AO.2021-12-01 AO.2022-01-01 AO.2022-02-01 AO.2022-03-01 AO.2022-04-01 AO.2022-05-01 AO.2022-06-01 AO.2022-07-01 AO.2023-02-01</items>
        </strings>
    </item>
</subset>
                            </item>
                        </subset>
                    </item>
                    <item name="benchmarking">
                        <subset/>
                    </item>
                </subset>
            </item>
        </subset>
    </item>
</informationSet>
